odoo9_addon_barcodes_generator_abstract-9.0.1.0.0.99.dev8-py3.8-nspkg.pth
odoo_addons/barcodes_generator_abstract/README.rst
odoo_addons/barcodes_generator_abstract/__init__.py
odoo_addons/barcodes_generator_abstract/__openerp__.py
odoo_addons/barcodes_generator_abstract/demo/res_users.xml
odoo_addons/barcodes_generator_abstract/i18n/am.po
odoo_addons/barcodes_generator_abstract/i18n/barcodes_generator_abstract.pot
odoo_addons/barcodes_generator_abstract/i18n/ca.po
odoo_addons/barcodes_generator_abstract/i18n/de.po
odoo_addons/barcodes_generator_abstract/i18n/el_GR.po
odoo_addons/barcodes_generator_abstract/i18n/es.po
odoo_addons/barcodes_generator_abstract/i18n/es_ES.po
odoo_addons/barcodes_generator_abstract/i18n/fi.po
odoo_addons/barcodes_generator_abstract/i18n/fr.po
odoo_addons/barcodes_generator_abstract/i18n/gl.po
odoo_addons/barcodes_generator_abstract/i18n/it.po
odoo_addons/barcodes_generator_abstract/i18n/nl.po
odoo_addons/barcodes_generator_abstract/i18n/pt.po
odoo_addons/barcodes_generator_abstract/i18n/pt_BR.po
odoo_addons/barcodes_generator_abstract/i18n/pt_PT.po
odoo_addons/barcodes_generator_abstract/i18n/sl.po
odoo_addons/barcodes_generator_abstract/i18n/tr.po
odoo_addons/barcodes_generator_abstract/models/__init__.py
odoo_addons/barcodes_generator_abstract/models/barcode_generate_mixin.py
odoo_addons/barcodes_generator_abstract/models/barcode_rule.py
odoo_addons/barcodes_generator_abstract/security/res_groups.xml
odoo_addons/barcodes_generator_abstract/static/description/barcode_rule_form_manual.png
odoo_addons/barcodes_generator_abstract/static/description/barcode_rule_form_sequence.png
odoo_addons/barcodes_generator_abstract/static/description/barcode_rule_tree.png
odoo_addons/barcodes_generator_abstract/static/description/icon.png
odoo_addons/barcodes_generator_abstract/views/menu.xml
odoo_addons/barcodes_generator_abstract/views/view_barcode_rule.xml
odoo9_addon_barcodes_generator_abstract-9.0.1.0.0.99.dev8.dist-info/METADATA
odoo9_addon_barcodes_generator_abstract-9.0.1.0.0.99.dev8.dist-info/WHEEL
odoo9_addon_barcodes_generator_abstract-9.0.1.0.0.99.dev8.dist-info/namespace_packages.txt
odoo9_addon_barcodes_generator_abstract-9.0.1.0.0.99.dev8.dist-info/top_level.txt
odoo9_addon_barcodes_generator_abstract-9.0.1.0.0.99.dev8.dist-info/RECORD
